{"cameraMode":{"drawMode":0,"name":"Shaded","section":"Shading Mode"},"sceneLighting":false,"audioPlay":false,"sceneViewState":{"showFog":true,"showMaterialUpdate":false,"showSkybox":false,"showFlares":true,"showImageEffects":true,"showParticleSystems":true},"in2DMode":false,"pivot":{"x":0.0010060667991638184,"y":2.6616246700286867,"z":0.056423839181661609},"rotation":{"x":-0.047828514128923419,"y":0.9437142610549927,"z":-0.1482110619544983,"w":-0.2929433286190033},"size":1.7217904329299927,"orthographic":false}